README.rst
setup.py
cricket/__init__.py
cricket/__main__.py
cricket/live_feed.py
cricket/rankings.py
cricket/score.py
cricket/stats.py
cricket_cli.egg-info/PKG-INFO
cricket_cli.egg-info/SOURCES.txt
cricket_cli.egg-info/dependency_links.txt
cricket_cli.egg-info/entry_points.txt
cricket_cli.egg-info/requires.txt
cricket_cli.egg-info/top_level.txt