Metadata-Version: 1.1
Name: cricket-cli
Version: 1.0.0b3
Summary: Command-line interface for cricket enthusiasts
Home-page: http://github.com/cbirajdar/cricket-cli
Author: Chetan Birajdar
Author-email: birajdar.chetan@gmail.com
License: MIT
Platform: UNKNOWN
Classifier: Development Status :: 4 - Beta
Classifier: Intended Audience :: Developers
Classifier: Natural Language :: English
Classifier: License :: OSI Approved :: MIT License
Classifier: Programming Language :: Python :: 2.7
Classifier: Programming Language :: Python :: 3.4
Classifier: Programming Language :: Python :: 3.5
